avirusplease/__init__.py
avirusplease/fun_stuff.py
avirusplease-0.0.2.dist-info/METADATA
avirusplease-0.0.2.dist-info/WHEEL
avirusplease-0.0.2.dist-info/top_level.txt
avirusplease-0.0.2.dist-info/RECORD
